pystatpower/__init__.py
pystatpower/__main__.py
pystatpower/numeric.py
pystatpower/option.py
pystatpower/models/__init__.py
pystatpower/models/one_proportion.py
pystatpower/models/two_proportion.py
pystatpower-0.0.3.dist-info/LICENSE
pystatpower-0.0.3.dist-info/METADATA
pystatpower-0.0.3.dist-info/WHEEL
pystatpower-0.0.3.dist-info/top_level.txt
pystatpower-0.0.3.dist-info/RECORD
