Metadata-Version: 2.1
Name: pystatpower
Version: 0.0.3
Summary: A Power Analysis Toolkit for Python
Author-email: Snoopy1866 <pystatpower@gmail.com>
License: GPL-3.0
Project-URL: Homepage, https://github.com/Snoopy1866/pystatpower
Project-URL: Documentation, https://github.com/Snoopy1866/pystatpower/blob/main/README.md
Project-URL: Repository, https://github.com/Snoopy1866/pystatpower.git
Project-URL: Issues, https://github.com/Snoopy1866/pystatpower/issues
Project-URL: Changelog, https://github.com/Snoopy1866/pystatpower/blob/main/CHANGELOG.md
Keywords: mathematics,statistics,power analysis,sample size,power,hypothesis
Classifier: Development Status :: 3 - Alpha
Classifier: Intended Audience :: Science/Research
Classifier: License :: OSI Approved :: GNU General Public License v3 (GPLv3)
Classifier: Operating System :: OS Independent
Classifier: Programming Language :: Python :: 3.10
Classifier: Programming Language :: Python :: 3.11
Classifier: Programming Language :: Python :: 3.12
Classifier: Programming Language :: Python :: 3.13
Classifier: Topic :: Scientific/Engineering :: Mathematics
Requires-Python: >=3.10
License-File: LICENSE
Requires-Dist: scipy>=1.12.0
Provides-Extra: dev
Requires-Dist: scipy>=1.12.0; extra == "dev"
Requires-Dist: esbonio==0.16.5; extra == "dev"
Requires-Dist: pre-commit==4.0.1; extra == "dev"
Requires-Dist: pytest==8.3.3; extra == "dev"
Requires-Dist: pytest-cov==6.0.0; extra == "dev"
Requires-Dist: ruff==0.8.0; extra == "dev"
Provides-Extra: docs
Requires-Dist: jieba==0.42.1; extra == "docs"
Requires-Dist: myst-parser==4.0.0; extra == "docs"
Requires-Dist: sphinx==8.1.3; extra == "docs"
Requires-Dist: sphinx-autobuild==2024.10.3; extra == "docs"
Requires-Dist: sphinx-autodoc2==0.5.0; extra == "docs"
Requires-Dist: sphinx-book-theme==1.1.3; extra == "docs"
Requires-Dist: sphinx-copybutton==0.5.2; extra == "docs"
Requires-Dist: sphinx-issues==5.0.0; extra == "docs"
Requires-Dist: sphinx-notfound-page==1.0.4; extra == "docs"
Requires-Dist: sphinx-togglebutton==0.3.2; extra == "docs"
Requires-Dist: sphinx_tippy==0.4.3; extra == "docs"
